django_admin_search_filter/__init__.py
django_admin_search_filter/templates/input_admin_filter.html
django_admin_search_filter-0.1.3.dist-info/LICENSE
django_admin_search_filter-0.1.3.dist-info/METADATA
django_admin_search_filter-0.1.3.dist-info/WHEEL
django_admin_search_filter-0.1.3.dist-info/RECORD
