Metadata-Version: 2.1
Name: django-admin-search-filter
Version: 0.1.3
Summary: Allows to create admin list filter as a search box for free-input
Home-page: https://github.com/mihasK/django-admin-search-filter/
Author: mihas
Author-email: mihasK@users.noreply.github.com
Requires-Python: >=3,<4
Classifier: Programming Language :: Python :: 3
Classifier: Programming Language :: Python :: 3.4
Classifier: Programming Language :: Python :: 3.5
Classifier: Programming Language :: Python :: 3.6
Classifier: Programming Language :: Python :: 3.7
Classifier: Programming Language :: Python :: 3.8
Classifier: Programming Language :: Python :: 3.9
Classifier: Programming Language :: Python :: 3.10
Classifier: Programming Language :: Python :: 3.11
Requires-Dist: django (>=2.2)
Project-URL: Repository, https://github.com/mihasK/django-admin-search-filter/
